changelog/__init__.py
changelog/__main__.py
changelog/cli/__init__.py
changelog/cli/config.py
changelog/cli/constants.py
changelog/cli/main.py
changelog/cli/state.py
changelog/exceptions.py
changelog/model.py
changelog/parser.py
changelog/py.typed
changelog/renderer.py
changelog/utils.py
changelog_cmd-0.2.0.dist-info/entry_points.txt
changelog_cmd-0.2.0.dist-info/LICENSE.txt
changelog_cmd-0.2.0.dist-info/WHEEL
changelog_cmd-0.2.0.dist-info/METADATA
changelog_cmd-0.2.0.dist-info/RECORD
