Metadata-Version: 2.1
Name: changelog-cmd
Version: 0.2.0
Summary: 
Home-page: https://github.com/jacksmith15/changelog-cmd
Author: Jack Smith
Author-email: jack.je.smith@gmail.com
Requires-Python: >=3.8,<4.0
Classifier: Programming Language :: Python :: 3
Classifier: Programming Language :: Python :: 3.8
Classifier: Programming Language :: Python :: 3.9
Requires-Dist: typer (>=0.3.2,<0.5.0)
Project-URL: Repository, https://github.com/jacksmith15/changelog-cmd
